shadcn_ui_maker/__about__.py
shadcn_ui_maker/__init__.py
shadcn_ui_maker-0.0.1.dist-info/METADATA
shadcn_ui_maker-0.0.1.dist-info/WHEEL
shadcn_ui_maker-0.0.1.dist-info/licenses/LICENSE.txt
shadcn_ui_maker-0.0.1.dist-info/RECORD
