Metadata-Version: 2.4
Name: shadcn-ui-maker
Version: 0.0.1
Project-URL: Documentation, https://github.com/pro-grammer-SD/shadcn-ui-maker#readme
Project-URL: Issues, https://github.com/pro-grammer-SD/shadcn-ui-maker/issues
Project-URL: Source, https://github.com/pro-grammer-SD/shadcn-ui-maker
Author-email: pro-grammer-SD <geniussantu1983@gmail.com>
License-Expression: MIT
License-File: LICENSE.txt
Classifier: Development Status :: 4 - Beta
Classifier: Programming Language :: Python
Classifier: Programming Language :: Python :: 3.8
Classifier: Programming Language :: Python :: 3.9
Classifier: Programming Language :: Python :: 3.10
Classifier: Programming Language :: Python :: 3.11
Classifier: Programming Language :: Python :: 3.12
Classifier: Programming Language :: Python :: Implementation :: CPython
Classifier: Programming Language :: Python :: Implementation :: PyPy
Requires-Python: >=3.8
